pyBiodatafuse/__init__.py
pyBiodatafuse/__main__.py
pyBiodatafuse/cli.py
pyBiodatafuse/constants.py
pyBiodatafuse/data_loader.py
pyBiodatafuse/human_homologs.py
pyBiodatafuse/id_annotator.py
pyBiodatafuse/id_mapper.py
pyBiodatafuse/utils.py
pyBiodatafuse/version.py
pyBiodatafuse/algorithms/DREAMwalk/HeterogeneousSG.cpp
pyBiodatafuse/algorithms/DREAMwalk/HeterogeneousSG.py
pyBiodatafuse/algorithms/DREAMwalk/calculate_drug_scores.py
pyBiodatafuse/algorithms/DREAMwalk/constant.py
pyBiodatafuse/algorithms/DREAMwalk/generate_embeddings.py
pyBiodatafuse/algorithms/DREAMwalk/generate_files.py
pyBiodatafuse/algorithms/DREAMwalk/generate_similarity_net.py
pyBiodatafuse/algorithms/DREAMwalk/predict_associations.py
pyBiodatafuse/algorithms/DREAMwalk/utils.py
pyBiodatafuse/analyzer/README.md
pyBiodatafuse/analyzer/summarize.py
pyBiodatafuse/analyzer/utils.py
pyBiodatafuse/analyzer/explorer/literature.py
pyBiodatafuse/analyzer/explorer/patent.py
pyBiodatafuse/analyzer/explorer/queries/wikidata-genes-literature.rq
pyBiodatafuse/annotators/__init__.py
pyBiodatafuse/annotators/aopwiki.py
pyBiodatafuse/annotators/bgee.py
pyBiodatafuse/annotators/disgenet.py
pyBiodatafuse/annotators/gprofiler.py
pyBiodatafuse/annotators/intact.py
pyBiodatafuse/annotators/kegg.py
pyBiodatafuse/annotators/minerva.py
pyBiodatafuse/annotators/mitocarta.py
pyBiodatafuse/annotators/molmedb.py
pyBiodatafuse/annotators/opentargets.py
pyBiodatafuse/annotators/pubchem.py
pyBiodatafuse/annotators/rdf_annotator_template.py
pyBiodatafuse/annotators/stringdb.py
pyBiodatafuse/annotators/tflink.py
pyBiodatafuse/annotators/wikidata.py
pyBiodatafuse/annotators/wikipathways.py
pyBiodatafuse/annotators/queries/aopwiki-compound.rq
pyBiodatafuse/annotators/queries/aopwiki-gene.rq
pyBiodatafuse/annotators/queries/aopwiki-metadata.rq
pyBiodatafuse/annotators/queries/bgee-genes-tissues-expression-level.rq
pyBiodatafuse/annotators/queries/bgee-get-last-modified.rq
pyBiodatafuse-1.2.0.dist-info/LICENSE
pyBiodatafuse-1.2.0.dist-info/METADATA
pyBiodatafuse-1.2.0.dist-info/WHEEL
pyBiodatafuse-1.2.0.dist-info/entry_points.txt
pyBiodatafuse-1.2.0.dist-info/top_level.txt
pyBiodatafuse-1.2.0.dist-info/RECORD
