Metadata-Version: 2.1
Name: pyBiodatafuse
Version: 1.2.0
Summary: A python package for integrating data from multiple resources
Home-page: https://github.com/BioDataFuse/pyBiodatafuse
Download-URL: https://github.com/BioDataFuse/pyBiodatafuse/releases
Author: Yojana Gadiya
Author-email: yojanagadiya@gmail.com
Maintainer: Tooba Abbassi-Daloii
Maintainer-email: t.abbassidaloii@maastrichtuniversity.nl
License: MIT
Project-URL: Tracker, https://github.com/BioDataFuse/pyBiodatafuse/issues
Project-URL: Source, https://github.com/BioDataFuse/pyBiodatafuse
Project-URL: Documentation, https://pyBiodatafuse.readthedocs.io
Keywords: snekpack,cookiecutter,drug-discvoery,knowledge graphs
Classifier: Development Status :: 1 - Planning
Classifier: Environment :: Console
Classifier: Intended Audience :: Developers
Classifier: License :: OSI Approved :: MIT License
Classifier: Operating System :: OS Independent
Classifier: Framework :: Pytest
Classifier: Framework :: tox
Classifier: Framework :: Sphinx
Classifier: Programming Language :: Python
Classifier: Programming Language :: Python :: 3.9
Classifier: Programming Language :: Python :: 3.10
Classifier: Programming Language :: Python :: 3.11
Classifier: Programming Language :: Python :: 3 :: Only
Requires-Python: >=3.9
License-File: LICENSE
Requires-Dist: pandas==2.0.3
Requires-Dist: tqdm==4.66.3
Requires-Dist: SPARQLWrapper
Requires-Dist: requests
Requires-Dist: click
Requires-Dist: matplotlib
Requires-Dist: seaborn==0.13.0
Requires-Dist: plotly==5.18.0
Requires-Dist: rdkit==2023.9.1
Requires-Dist: pubchempy==1.0.4
Requires-Dist: nbformat==5.9.2
Requires-Dist: networkx
Requires-Dist: xlrd>=2.0.1
Requires-Dist: neo4j>=5.14
Requires-Dist: numpy==1.24.4
Requires-Dist: tabulate==0.8.9
Requires-Dist: xgboost==1.7.4
Requires-Dist: parmap==1.6.0
Requires-Dist: scipy==1.10.1
Requires-Dist: scikit-learn==1.1.3
Requires-Dist: rdflib==7.0.0
Requires-Dist: shexer==2.5.9
Requires-Dist: bioregistry==0.11.10
Requires-Dist: neomodel==5.4.5
Requires-Dist: py4cytoscape==1.12.0
Requires-Dist: gprofiler-official==1.0.0
Provides-Extra: docs
Requires-Dist: sphinx; extra == "docs"
Requires-Dist: sphinx-rtd-theme; extra == "docs"
Requires-Dist: sphinx-click; extra == "docs"
Requires-Dist: sphinx-automodapi; extra == "docs"
Provides-Extra: tests
Requires-Dist: pytest; extra == "tests"
Requires-Dist: coverage; extra == "tests"
